plaid/__init__.py
plaid/_version.py
plaid/constants.py
plaid/problem_definition.py
plaid/bridges/__init__.py
plaid/bridges/huggingface_bridge.py
plaid/bridges/huggingface_helpers.py
plaid/containers/__init__.py
plaid/containers/dataset.py
plaid/containers/feature_identifier.py
plaid/containers/features.py
plaid/containers/sample.py
plaid/containers/utils.py
plaid/containers/managers/__init__.py
plaid/containers/managers/default_manager.py
plaid/examples/__init__.py
plaid/examples/config.py
plaid/examples/dataset.py
plaid/examples/sample.py
plaid/pipelines/__init__.py
plaid/pipelines/plaid_blocks.py
plaid/pipelines/sklearn_block_wrappers.py
plaid/post/__init__.py
plaid/post/bisect.py
plaid/post/metrics.py
plaid/storage/__init__.py
plaid/storage/reader.py
plaid/storage/registry.py
plaid/storage/writer.py
plaid/storage/cgns/__init__.py
plaid/storage/cgns/reader.py
plaid/storage/cgns/writer.py
plaid/storage/common/__init__.py
plaid/storage/common/bridge.py
plaid/storage/common/preprocessor.py
plaid/storage/common/reader.py
plaid/storage/common/writer.py
plaid/storage/hf_datasets/__init__.py
plaid/storage/hf_datasets/bridge.py
plaid/storage/hf_datasets/reader.py
plaid/storage/hf_datasets/writer.py
plaid/storage/zarr/__init__.py
plaid/storage/zarr/bridge.py
plaid/storage/zarr/reader.py
plaid/storage/zarr/writer.py
plaid/types/__init__.py
plaid/types/cgns_types.py
plaid/types/common.py
plaid/types/feature_types.py
plaid/types/sklearn_types.py
plaid/utils/__init__.py
plaid/utils/base.py
plaid/utils/cgns_helper.py
plaid/utils/cgns_worker.py
plaid/utils/deprecation.py
plaid/utils/init_with_tabular.py
plaid/utils/interpolation.py
plaid/utils/split.py
plaid/utils/stats.py
pyplaid-0.1.13.dist-info/licenses/LICENSE.txt
pyplaid-0.1.13.dist-info/METADATA
pyplaid-0.1.13.dist-info/WHEEL
pyplaid-0.1.13.dist-info/top_level.txt
pyplaid-0.1.13.dist-info/RECORD
