Metadata-Version: 2.4
Name: pyplaid
Version: 0.1.13
Summary: A package that implements a data model tailored for AI and ML in the context of physics problems
Author-email: Safran <fabien.casenave@safrangroup.com>
License: BSD 3-Clause License
Project-URL: homepage, https://plaid-lib.github.io
Project-URL: documentation, https://plaid-lib.readthedocs.io
Project-URL: repository, https://github.com/PLAID-lib/plaid
Keywords: machine learning,physics,data-model,Safran
Platform: Linux
Platform: Mac OS-X
Platform: Unix
Classifier: Intended Audience :: Science/Research
Classifier: License :: OSI Approved :: BSD License
Classifier: Operating System :: MacOS
Classifier: Operating System :: POSIX
Classifier: Operating System :: Microsoft :: Windows
Classifier: Programming Language :: Python :: 3.11
Classifier: Programming Language :: Python :: 3.12
Classifier: Programming Language :: Python :: 3.13
Classifier: Topic :: Scientific/Engineering
Classifier: Topic :: Scientific/Engineering :: Artificial Intelligence
Classifier: Topic :: Scientific/Engineering :: Mathematics
Requires-Python: <3.14,>=3.11
License-File: LICENSE.txt
Requires-Dist: tqdm
Requires-Dist: pyyaml
Requires-Dist: pycgns
Requires-Dist: zarr
Requires-Dist: scikit-learn
Requires-Dist: datasets
Requires-Dist: numpy
Requires-Dist: matplotlib
Requires-Dist: pydantic
Provides-Extra: dev
Requires-Dist: rich; extra == "dev"
Requires-Dist: optuna; extra == "dev"
Requires-Dist: pytest; extra == "dev"
Requires-Dist: pytest-cov; extra == "dev"
Requires-Dist: ruff; extra == "dev"
Requires-Dist: pre-commit; extra == "dev"
Requires-Dist: sphinx; extra == "dev"
Requires-Dist: sphinx-autoapi; extra == "dev"
Requires-Dist: sphinx-tabs; extra == "dev"
Requires-Dist: sphinxcontrib.bibtex; extra == "dev"
Requires-Dist: myst-nb; extra == "dev"
Requires-Dist: myst-parser; extra == "dev"
Requires-Dist: furo; extra == "dev"
Requires-Dist: jupytext; extra == "dev"
Dynamic: license-file
